pySDCP-1.dist-info/DESCRIPTION.rst
pySDCP-1.dist-info/METADATA
pySDCP-1.dist-info/RECORD
pySDCP-1.dist-info/WHEEL
pySDCP-1.dist-info/metadata.json
pySDCP-1.dist-info/top_level.txt
pysdcp/__init__.py
pysdcp/protocol.py
