Metadata-Version: 1.2
Name: pySDCP
Version: 1
Summary: SDCP library to control Sony Projectors
Home-page: https://github.com/Galala7/pySDCP
Author: Guy Shapira
Author-email: Galala7@users.noreply.github.com
License: MIT
Platform: UNKNOWN
Classifier: Development Status :: 4 - Beta
Classifier: Intended Audience :: Developers
Classifier: Topic :: Software Development :: Build Tools
Classifier: License :: OSI Approved :: MIT License
Classifier: Programming Language :: Python :: 3.6
Requires-Python: >=3
